Workbook
Name UseMonthlyVolume: Inputs!$B$20
Name VolumePerDay: Inputs!$B$2
Name VolumePerMonth: Inputs!$B$21
Name WorkingDays: Inputs!$B$3
Name ManualMinutes: Inputs!$B$4
Name LoadedCostPerHour: Inputs!$B$5
Name ManualErrorRate: Inputs!$B$6
Name AgentErrorRate: Inputs!$B$7
Name CostOfError: Inputs!$B$8
Name InputTokens: Inputs!$B$9
Name OutputTokens: Inputs!$B$10
Name InputPricePerMillion: Inputs!$B$11
Name OutputPricePerMillion: Inputs!$B$12
Name ReviewMinutes: Inputs!$B$13
Name ReviewRate: Inputs!$B$14
Name ImplementationCost: Inputs!$B$15
Name MonthlyRunCost: Inputs!$B$16
Name AdoptionRamp: Inputs!$B$17
Name DiscountRate: Inputs!$B$18

Sheet Inputs
A1: key | B1: value | C1: unit | D1: rationale
A2: volume_per_day | B2: 120 | C2: items/day | D2: [EST] Planning volume for a mid-size fictional returns desk, not a count from a warehouse.
A3: working_days_per_month | B3: 21 | C3: days/month | D3: [EST] A conventional business month. It is not this company's calendar.
A4: manual_minutes_per_item | B4: 12 | C4: minutes | D4: [EST] Time to read a return, check policy and type a decision without an agent.
A5: loaded_cost_per_hour | B5: 32 | C5: USD/hour | D5: [EST] Loaded desk cost, not a wage from a payroll system.
A6: manual_error_rate | B6: 0.06 | C6: fraction | D6: [EST] Share of manual decisions that need rework or a goodwill payment.
A7: agent_error_rate | B7: 0.02 | C7: fraction | D7: [EST] Residual errors after the review policy. Not a measured model score.
A8: cost_of_error | B8: 25 | C8: USD/error | D8: [EST] Average cost of one bad refund decision, goodwill plus rework.
A9: input_tokens | B9: 1800 | C9: tokens | D9: [EST] Prompt size for one case file. Not a trace from a provider.
A10: output_tokens | B10: 400 | C10: tokens | D10: [EST] Draft length. Not a measured completion.
A11: input_price_per_million | B11: 1.5 | C11: USD/1M tokens | D11: [EST] Illustrative blended price. Not copied from a vendor price page.
A12: output_price_per_million | B12: 6 | C12: USD/1M tokens | D12: [EST] Illustrative blended price. Not copied from a vendor price page.
A13: review_minutes | B13: 5 | C13: minutes | D13: [EST] Time a person spends when a case is routed to review.
... A18: discount_rate_annual | B18: 0.1 | C18: fraction | D18: [EST] Annual discount rate for a 3-year NPV. Not a treasury rate.
A20: use_monthly_volume | B20: 0 | D20: 1 when the case is stated per month
A21: volume_per_month | B21: 0 | D21: unused in this volume mode

Sheet Model
A1: metric | B1: formula
A2: agent_run_cost | B2: =InputTokens/1000000*InputPricePerMillion+OutputTokens/1000000*OutputPricePerMillion
A3: manual_labor | B3: =ManualMinutes/60*LoadedCostPerHour
A4: manual_error | B4: =ManualErrorRate*CostOfError
A5: review_cost | B5: =ReviewRate*(ReviewMinutes/60)*LoadedCostPerHour
A6: residual_error | B6: =AgentErrorRate*CostOfError
A7: quality_adjusted_savings | B7: =B3+B4-(B2+B5)-B6
A8: monthly_volume_steady | B8: =IF(UseMonthlyVolume=1,VolumePerMonth,VolumePerDay*WorkingDays)
A9: net_monthly_steady | B9: =B8*B7-MonthlyRunCost
A10: break_even_volume | B10: =IF(B7<=0,"never",MonthlyRunCost/B7)
A11: monthly_discount_rate | B11: =(1+DiscountRate)^(1/12)-1
A12: npv | B12: =-ImplementationCost+SUM(Cashflows!E2:E361)
A13: payback_months | B13: =IF(COUNT(Cashflows!H2:H361)=0,"never",SUM(Cashflows!H2:H361))

Sheet Cashflows
A1: month | B1: adoption | C1: volume | D1: net | E1: discounted | F1: cumulative | G1: blank | H1: payback_piece
A2: =1 | B2: =IF(AdoptionRamp<=0,1,MIN(1,A2/AdoptionRamp)) | C2: =Model!$B$8*B2 | D2: =C2*Model!$B$7-MonthlyRunCost | E2: =D2/(1+Model!$B$11)^A2 | F2: =-ImplementationCost+D2 | H2: =IF(F2>=0,IF(D2<=0,0,ImplementationCost/D2),"")
A3: =A2+1 | B3: =IF(AdoptionRamp<=0,1,MIN(1,A3/AdoptionRamp)) | C3: =Model!$B$8*B3 | D3: =C3*Model!$B$7-MonthlyRunCost | E3: =D3/(1+Model!$B$11)^A3 | F3: =F2+D3 | H3: =IF(AND(F3>=0,F2<0),(A3-1)+IF(D3<=0,0,-F2/D3),"")
A4: =A3+1 | B4: =IF(AdoptionRamp<=0,1,MIN(1,A4/AdoptionRamp)) | C4: =Model!$B$8*B4 | D4: =C4*Model!$B$7-MonthlyRunCost | E4: =D4/(1+Model!$B$11)^A4 | F4: =F3+D4 | H4: =IF(AND(F4>=0,F3<0),(A4-1)+IF(D4<=0,0,-F3/D4),"")
A5: =A4+1 | B5: =IF(AdoptionRamp<=0,1,MIN(1,A5/AdoptionRamp)) | C5: =Model!$B$8*B5 | D5: =C5*Model!$B$7-MonthlyRunCost | E5: =D5/(1+Model!$B$11)^A5 | F5: =F4+D5 | H5: =IF(AND(F5>=0,F4<0),(A5-1)+IF(D5<=0,0,-F4/D5),"")
A6: =A5+1 | B6: =IF(AdoptionRamp<=0,1,MIN(1,A6/AdoptionRamp)) | C6: =Model!$B$8*B6 | D6: =C6*Model!$B$7-MonthlyRunCost | E6: =D6/(1+Model!$B$11)^A6 | F6: =F5+D6 | H6: =IF(AND(F6>=0,F5<0),(A6-1)+IF(D6<=0,0,-F5/D6),"")
A7: =A6+1 | B7: =IF(AdoptionRamp<=0,1,MIN(1,A7/AdoptionRamp)) | C7: =Model!$B$8*B7 | D7: =C7*Model!$B$7-MonthlyRunCost | E7: =D7/(1+Model!$B$11)^A7 | F7: =F6+D7 | H7: =IF(AND(F7>=0,F6<0),(A7-1)+IF(D7<=0,0,-F6/D7),"")
A8: =A7+1 | B8: =IF(AdoptionRamp<=0,1,MIN(1,A8/AdoptionRamp)) | C8: =Model!$B$8*B8 | D8: =C8*Model!$B$7-MonthlyRunCost | E8: =D8/(1+Model!$B$11)^A8 | F8: =F7+D8 | H8: =IF(AND(F8>=0,F7<0),(A8-1)+IF(D8<=0,0,-F7/D8),"")
A9: =A8+1 | B9: =IF(AdoptionRamp<=0,1,MIN(1,A9/AdoptionRamp)) | C9: =Model!$B$8*B9 | D9: =C9*Model!$B$7-MonthlyRunCost | E9: =D9/(1+Model!$B$11)^A9 | F9: =F8+D9 | H9: =IF(AND(F9>=0,F8<0),(A9-1)+IF(D9<=0,0,-F8/D9),"")
A10: =A9+1 | B10: =IF(AdoptionRamp<=0,1,MIN(1,A10/AdoptionRamp)) | C10: =Model!$B$8*B10 | D10: =C10*Model!$B$7-MonthlyRunCost | E10: =D10/(1+Model!$B$11)^A10 | F10: =F9+D10 | H10: =IF(AND(F10>=0,F9<0),(A10-1)+IF(D10<=0,0,-F9/D10),"")
A11: =A10+1 | B11: =IF(AdoptionRamp<=0,1,MIN(1,A11/AdoptionRamp)) | C11: =Model!$B$8*B11 | D11: =C11*Model!$B$7-MonthlyRunCost | E11: =D11/(1+Model!$B$11)^A11 | F11: =F10+D11 | H11: =IF(AND(F11>=0,F10<0),(A11-1)+IF(D11<=0,0,-F10/D11),"")
A12: =A11+1 | B12: =IF(AdoptionRamp<=0,1,MIN(1,A12/AdoptionRamp)) | C12: =Model!$B$8*B12 | D12: =C12*Model!$B$7-MonthlyRunCost | E12: =D12/(1+Model!$B$11)^A12 | F12: =F11+D12 | H12: =IF(AND(F12>=0,F11<0),(A12-1)+IF(D12<=0,0,-F11/D12),"")
A13: =A12+1 | B13: =IF(AdoptionRamp<=0,1,MIN(1,A13/AdoptionRamp)) | C13: =Model!$B$8*B13 | D13: =C13*Model!$B$7-MonthlyRunCost | E13: =D13/(1+Model!$B$11)^A13 | F13: =F12+D13 | H13: =IF(AND(F13>=0,F12<0),(A13-1)+IF(D13<=0,0,-F12/D13),"")
A14: =A13+1 | B14: =IF(AdoptionRamp<=0,1,MIN(1,A14/AdoptionRamp)) | C14: =Model!$B$8*B14 | D14: =C14*Model!$B$7-MonthlyRunCost | E14: =D14/(1+Model!$B$11)^A14 | F14: =F13+D14 | H14: =IF(AND(F14>=0,F13<0),(A14-1)+IF(D14<=0,0,-F13/D14),"")
... A37: =A36+1 | B37: =IF(AdoptionRamp<=0,1,MIN(1,A37/AdoptionRamp)) | C37: =Model!$B$8*B37 | D37: =C37*Model!$B$7-MonthlyRunCost | E37: =D37/(1+Model!$B$11)^A37 | F37: =F36+D37 | H37: =IF(AND(F37>=0,F36<0),(A37-1)+IF(D37<=0,0,-F36/D37),"")
A38: =A37+1 | B38: =IF(AdoptionRamp<=0,1,MIN(1,A38/AdoptionRamp)) | C38: =Model!$B$8*B38 | D38: =C38*Model!$B$7-MonthlyRunCost | E38: 0 | F38: =F37+D38 | H38: =IF(AND(F38>=0,F37<0),(A38-1)+IF(D38<=0,0,-F37/D38),"")
A39: =A38+1 | B39: =IF(AdoptionRamp<=0,1,MIN(1,A39/AdoptionRamp)) | C39: =Model!$B$8*B39 | D39: =C39*Model!$B$7-MonthlyRunCost | E39: 0 | F39: =F38+D39 | H39: =IF(AND(F39>=0,F38<0),(A39-1)+IF(D39<=0,0,-F38/D39),"")
A40: =A39+1 | B40: =IF(AdoptionRamp<=0,1,MIN(1,A40/AdoptionRamp)) | C40: =Model!$B$8*B40 | D40: =C40*Model!$B$7-MonthlyRunCost | E40: 0 | F40: =F39+D40 | H40: =IF(AND(F40>=0,F39<0),(A40-1)+IF(D40<=0,0,-F39/D40),"")
A41: =A40+1 | B41: =IF(AdoptionRamp<=0,1,MIN(1,A41/AdoptionRamp)) | C41: =Model!$B$8*B41 | D41: =C41*Model!$B$7-MonthlyRunCost | E41: 0 | F41: =F40+D41 | H41: =IF(AND(F41>=0,F40<0),(A41-1)+IF(D41<=0,0,-F40/D41),"")
A42: =A41+1 | B42: =IF(AdoptionRamp<=0,1,MIN(1,A42/AdoptionRamp)) | C42: =Model!$B$8*B42 | D42: =C42*Model!$B$7-MonthlyRunCost | E42: 0 | F42: =F41+D42 | H42: =IF(AND(F42>=0,F41<0),(A42-1)+IF(D42<=0,0,-F41/D42),"")
A43: =A42+1 | B43: =IF(AdoptionRamp<=0,1,MIN(1,A43/AdoptionRamp)) | C43: =Model!$B$8*B43 | D43: =C43*Model!$B$7-MonthlyRunCost | E43: 0 | F43: =F42+D43 | H43: =IF(AND(F43>=0,F42<0),(A43-1)+IF(D43<=0,0,-F42/D43),"")
A44: =A43+1 | B44: =IF(AdoptionRamp<=0,1,MIN(1,A44/AdoptionRamp)) | C44: =Model!$B$8*B44 | D44: =C44*Model!$B$7-MonthlyRunCost | E44: 0 | F44: =F43+D44 | H44: =IF(AND(F44>=0,F43<0),(A44-1)+IF(D44<=0,0,-F43/D44),"")
A45: =A44+1 | B45: =IF(AdoptionRamp<=0,1,MIN(1,A45/AdoptionRamp)) | C45: =Model!$B$8*B45 | D45: =C45*Model!$B$7-MonthlyRunCost | E45: 0 | F45: =F44+D45 | H45: =IF(AND(F45>=0,F44<0),(A45-1)+IF(D45<=0,0,-F44/D45),"")
A46: =A45+1 | B46: =IF(AdoptionRamp<=0,1,MIN(1,A46/AdoptionRamp)) | C46: =Model!$B$8*B46 | D46: =C46*Model!$B$7-MonthlyRunCost | E46: 0 | F46: =F45+D46 | H46: =IF(AND(F46>=0,F45<0),(A46-1)+IF(D46<=0,0,-F45/D46),"")
A47: =A46+1 | B47: =IF(AdoptionRamp<=0,1,MIN(1,A47/AdoptionRamp)) | C47: =Model!$B$8*B47 | D47: =C47*Model!$B$7-MonthlyRunCost | E47: 0 | F47: =F46+D47 | H47: =IF(AND(F47>=0,F46<0),(A47-1)+IF(D47<=0,0,-F46/D47),"")
A48: =A47+1 | B48: =IF(AdoptionRamp<=0,1,MIN(1,A48/AdoptionRamp)) | C48: =Model!$B$8*B48 | D48: =C48*Model!$B$7-MonthlyRunCost | E48: 0 | F48: =F47+D48 | H48: =IF(AND(F48>=0,F47<0),(A48-1)+IF(D48<=0,0,-F47/D48),"")
A49: =A48+1 | B49: =IF(AdoptionRamp<=0,1,MIN(1,A49/AdoptionRamp)) | C49: =Model!$B$8*B49 | D49: =C49*Model!$B$7-MonthlyRunCost | E49: 0 | F49: =F48+D49 | H49: =IF(AND(F49>=0,F48<0),(A49-1)+IF(D49<=0,0,-F48/D49),"")
... A361: =A360+1 | B361: =IF(AdoptionRamp<=0,1,MIN(1,A361/AdoptionRamp)) | C361: =Model!$B$8*B361 | D361: =C361*Model!$B$7-MonthlyRunCost | E361: 0 | F361: =F360+D361 | H361: =IF(AND(F361>=0,F360<0),(A361-1)+IF(D361<=0,0,-F360/D361),"")
